topsis/__init__.py
topsis/topsis.py
Topsis_Nikhil_Garg_102203275-1.0.1.dist-info/METADATA
Topsis_Nikhil_Garg_102203275-1.0.1.dist-info/WHEEL
Topsis_Nikhil_Garg_102203275-1.0.1.dist-info/top_level.txt
Topsis_Nikhil_Garg_102203275-1.0.1.dist-info/RECORD
