Metadata-Version: 2.1
Name: Topsis-Nikhil-Garg-102203275
Version: 1.0.1
Summary: A Python package for performing TOPSIS analysis.
Home-page: https://github.com/Bluebird5757/Topsis_Nikhil_Garg_102203275
Author: Nikhil_Garg
Author-email: nikhilgarg288@gmail.com
Classifier: Programming Language :: Python :: 3
Classifier: License :: OSI Approved :: MIT License
Classifier: Operating System :: OS Independent
Requires-Python: >=3.6
Requires-Dist: pandas
Requires-Dist: numpy
Requires-Dist: openpyxl
